{
 "actions": [],
 "creation": "2021-12-02 10:09:48.972142",
 "doctype": "DocType",
 "editable_grid": 1,
 "engine": "InnoDB",
 "field_order": [
  "revision",
  "enquiry_received_date",
  "type_of_effluent",
  "capacity",
  "proposed_scheme",
  "tds_mgl",
  "cod_mgl",
  "proposal_sent_date",
  "reason_for_revision",
  "notes"
 ],
 "fields": [
  {
   "columns": 1,
   "fieldname": "revision",
   "fieldtype": "Data",
   "in_list_view": 1,
   "label": "Revision"
  },
  {
   "columns": 2,
   "fieldname": "enquiry_received_date",
   "fieldtype": "Date",
   "in_list_view": 1,
   "label": "Enquiry received date"
  },
  {
   "columns": 1,
   "fieldname": "type_of_effluent",
   "fieldtype": "Data",
   "in_list_view": 1,
   "label": "Type of effluent"
  },
  {
   "columns": 1,
   "fieldname": "capacity",
   "fieldtype": "Data",
   "in_list_view": 1,
   "label": "Capacity"
  },
  {
   "columns": 2,
   "fieldname": "proposed_scheme",
   "fieldtype": "Data",
   "in_list_view": 1,
   "label": "Proposed scheme"
  },
  {
   "columns": 1,
   "fieldname": "tds_mgl",
   "fieldtype": "Data",
   "label": "TDS (mg/l)"
  },
  {
   "columns": 1,
   "fieldname": "cod_mgl",
   "fieldtype": "Data",
   "label": "COD (mg/l)"
  },
  {
   "columns": 2,
   "fieldname": "proposal_sent_date",
   "fieldtype": "Date",
   "in_list_view": 1,
   "label": "Proposal sent date"
  },
  {
   "columns": 2,
   "fieldname": "reason_for_revision",
   "fieldtype": "Small Text",
   "label": "Reason for Revision"
  },
  {
   "fieldname": "notes",
   "fieldtype": "Small Text",
   "label": "Remarks"
  }
 ],
 "index_web_pages_for_search": 1,
 "istable": 1,
 "links": [],
 "modified": "2021-12-02 11:33:25.374346",
 "modified_by": "Administrator",
 "module": "wtt_module",
 "name": "History Table",
 "owner": "Administrator",
 "permissions": [],
 "sort_field": "modified",
 "sort_order": "DESC",
 "track_changes": 1
}